SupersoundReconstruction/SRImage.py
SupersoundReconstruction/SRR.py
SupersoundReconstruction/SRRead.py
SupersoundReconstruction/__init__.py
SupersoundReconstruction/image.py
SupersoundReconstruction/matrix.py
SupersoundReconstruction/point.py
SupersoundReconstruction/readfile.py
heartsupersound/__init__.py
heartsupersound/image.py
heartsupersound/matrix.py
heartsupersound/point.py
heartsupersound/readfile.py
supersound_r/__init__.py
supersound_r/image.py
supersound_r/matrix.py
supersound_r/point.py
supersound_r/readfile.py
heartsupersound-0.0.11.dist-info/LICENSE
heartsupersound-0.0.11.dist-info/METADATA
heartsupersound-0.0.11.dist-info/WHEEL
heartsupersound-0.0.11.dist-info/top_level.txt
heartsupersound-0.0.11.dist-info/RECORD
