Metadata-Version: 2.1
Name: heartsupersound
Version: 0.0.11
Summary: a package for supersound
Home-page: https://gitee.com/wang2wan/SupersoundReconstruction_project
Author: GentleWang
Author-email: 189030005@stu.just.edu.cn
License: MIT
Classifier: Programming Language :: Python :: 3
Classifier: License :: OSI Approved :: MIT License
Classifier: Operating System :: OS Independent
Requires-Python: >=3.6
License-File: LICENSE
Requires-Dist: numpy
Requires-Dist: json5
Requires-Dist: opencv-python
